{
  "bookId": "psalms",
  "book": "Abụ Ọma",
  "chapter": 140,
  "verses": [
    {
      "verse": 1,
      "text": "O Onyenwe anyị, dọpụta m site nʼaka ndị na-eme ihe ọjọọ. Chebe m ka m ghara ịdaba nʼaka ndị na-eme ihe ike dị iche iche."
    },
    {
      "verse": 2,
      "text": "Ndị na-atụ atụmatụ ime ihe ọjọọ nʼobi ha na-akpali agha ụbọchị niile."
    },
    {
      "verse": 3,
      "text": "Ha na-eme ire ha ka ha dị nkọ dịka nke agwọ; elo ajụala dị nʼegbugbere ọnụ ha. Sela"
    },
    {
      "verse": 4,
      "text": "Chebe m Onyenwe anyị, ka m ghara ịdaba nʼaka ndị na-emebi iwu; chebe m ka m ghara ịdaba nʼaka ndị na-eme ihe ike, ndị na-eche echiche ọdịda m."
    },
    {
      "verse": 5,
      "text": "Ndị mpako esielera m ọnya igbudu; ha agbasaala ụgbụ ha na udo ha, siekwara m ọnya dị iche iche nʼụzọ m na-aga. Sela"
    },
    {
      "verse": 6,
      "text": "A sịrị m Onyenwe anyị, “Gị onwe gị bụ Chineke m.” Nụrụ, O Onyenwe anyị, olu arịrịọ m maka amara."
    },
    {
      "verse": 7,
      "text": "Onye kachasị ihe niile elu, bụ Onyenwe anyị Onye nzọpụta m dị ike, ị na-ekpuchi isi m nʼụbọchị agha."
    },
    {
      "verse": 8,
      "text": "Ekwekwala ka ndị ajọ omume chọta ihe ha na-achọ, o Onyenwe anyị, ekwekwala ka nzube ha mezuo. Sela"
    },
    {
      "verse": 9,
      "text": "Ndị niile gbara m gburugburu na-ebuli isi ha elu na nganga ka ndụ ọjọọ nke egbugbere ọnụ ha rikpuo ha."
    },
    {
      "verse": 10,
      "text": "Ka icheku ọkụ na-ere ere dakwasị ha; ka a tụba ha nʼime ọkụ na-ere ere, nʼime olulu apịtị jupụtara, nke ha na-enweghị ike isite nʼime ya pụta ọzọ."
    },
    {
      "verse": 11,
      "text": "Ekwela ka ndị na-ekwu okwu nkwulu guzosie ike nʼala, ka ihe ọjọọ chụda ndị na-eme ihe ike."
    },
    {
      "verse": 12,
      "text": "Amaara m na Onyenwe anyị ga-ekpe ikpe ziri ezi nye ndị ogbenye na-emekwa ka ndị nọ na mkpa nweta ihe ruuru ha."
    },
    {
      "verse": 13,
      "text": "Nʼezie, ndị ezi omume ga-eto aha gị, ndị ziri ezi ga-ebikwa nʼihu gị."
    }
  ]
}