{
  "bookId": "proverbs",
  "book": "Karin Magana",
  "chapter": 27,
  "verses": [
    {
      "verse": 1,
      "text": "Kada ka yi fariya a kan gobe gama ba san abin da ranar za tă kawo ba."
    },
    {
      "verse": 2,
      "text": "Ka bar wani ya yabe ka, ba kai kanka ba; wani dabam, ba leɓunanka ba."
    },
    {
      "verse": 3,
      "text": "Dutse yana da nauyi yashi kuma wahala ce, amma tsokanar wawa ta fi su duka nauyi."
    },
    {
      "verse": 4,
      "text": "Fushi mugun abu ne mai hallakarwa, amma wa zai iya tsaya a gaban kishi?"
    },
    {
      "verse": 5,
      "text": "Gara tsawatawar da ake yi a fili da ƙaunar da ake yi a ɓoye."
    },
    {
      "verse": 6,
      "text": "Za a iya amince da rauni daga aboki, amma abokin gāba ko da ya sumbace ka kada ka sake da shi!"
    },
    {
      "verse": 7,
      "text": "Duk wanda ya ƙoshi da zuma, ba ya marmarinsa kuma amma wanda yake yunwa ko abin da yake da ɗaci ma zai ji shi da zaƙi."
    },
    {
      "verse": 8,
      "text": "Kamar tsuntsun da ya ɓace daga sheƙarsa haka yake da mutumin da ya bar gidansa."
    },
    {
      "verse": 9,
      "text": "Man shafawa mai ƙanshi da kuma turare kan faranta zuciya, gaisuwar amini kuma takan fito daga shawarar kirki."
    },
    {
      "verse": 10,
      "text": "Kada ka manta da abokinka da kuma abokin mahaifinka, kuma kada ka tafi gidan ɗan’uwanka sa’ad da masifa ta same ka, gara ka je wurin maƙwabci na kusa da ka je wurin ɗan’uwan da yake da nisa."
    },
    {
      "verse": 11,
      "text": "Ka zama mai hikima, ɗana, ka kuma faranta mini zuciya; zan iya amsa kowace irin suƙar da wani zai yi mini."
    },
    {
      "verse": 12,
      "text": "Mai basira kan hango hatsari ya kuma kauce, marar azanci zai yi ta kutsa kai ciki, daga baya ya yi da na sani."
    },
    {
      "verse": 13,
      "text": "A karɓe rigunan wanda ya ɗauki lamunin baƙo; a riƙe shi jingina in ya yi shi don mace marar aminci."
    },
    {
      "verse": 14,
      "text": "In mutum ya albarkaci maƙwabcinsa da murya mai ƙarfi da sassafe, za a ɗauka shi a matsayin la’ana."
    },
    {
      "verse": 15,
      "text": "Mace mai fitina kamar ɗiɗɗigar ruwa take ba ƙaƙƙautawa;"
    },
    {
      "verse": 16,
      "text": "hana ta yana kamar yin ƙoƙari tsai da iska ne ko yin ƙoƙarin cafke mai a tafin hannunka."
    },
    {
      "verse": 17,
      "text": "Kamar yadda ƙarfe kan wasa ƙarfe haka mutum kan koyi daga mutum."
    },
    {
      "verse": 18,
      "text": "Duk wanda ya lura da itacen ɓaure, zai ci ’ya’yansa, kuma duk wanda ya lura da maigidansa za a girmama shi."
    },
    {
      "verse": 19,
      "text": "Kamar yadda ruwa kan nuna yadda fuska take, haka zuciyar mutum kan nuna irin mutumin."
    },
    {
      "verse": 20,
      "text": "Mutuwa da Hallaka ba sa ƙoshi, haka idanun mutum ba sa ƙoshi da gani."
    },
    {
      "verse": 21,
      "text": "Ana gwajin azurfa da kuma zinariya da wuta, amma akan gwada mutum ta wurin yabon da ya samu."
    },
    {
      "verse": 22,
      "text": "Ko da ka daka wawa a turmi, kana daka shi kamar hatsi da taɓarya, ba za ka fid da wauta daga gare shi ba."
    },
    {
      "verse": 23,
      "text": "Ka tabbata ka san lafiyar garken tumakinka, ka mai da hankali ga garken shanunka;"
    },
    {
      "verse": 24,
      "text": "domin dukiya ba ta dawwama har abada, ba a kuma kasance da rawani daga tsara zuwa tsara."
    },
    {
      "verse": 25,
      "text": "Sa’ad da aka yanki ingirci sabon toho kuma ya bayyana aka kuma tattara ciyawa daga tuddai,"
    },
    {
      "verse": 26,
      "text": "gashin raguna za su tanada maka tufafi, za ka iya sayi gonaki masu kyau da kuɗin awaki."
    },
    {
      "verse": 27,
      "text": "Za ka kasance da madarar awaki mai yawa don ka ciyar da kanka da kuma iyalinka ka kuma inganta bayinka mata."
    }
  ]
}