{
  "bookId": "john",
  "book": "Yohanna",
  "chapter": 20,
  "verses": [
    {
      "verse": 1,
      "text": "Da sassafe a ranar farko ta mako, tun da sauran duhu, Maryamu Magdalin ta tafi kabarin ta kuwa tarar an kawar da dutsen daga bakin kabarin."
    },
    {
      "verse": 2,
      "text": "Sai ta zo da gudu wajen Siman Bitrus da ɗayan almajirin, wanda Yesu yake ƙauna, ta ce, “Sun ɗauke Ubangiji daga kabarin, ba mu kuma san inda suka sa shi ba!”"
    },
    {
      "verse": 3,
      "text": "Sai Bitrus da almajirin nan suka nufi kabarin."
    },
    {
      "verse": 4,
      "text": "Dukansu biyu suna gudu, amma ɗayan almajirin ya tsere wa Bitrus ya kuma fara kai kabarin."
    },
    {
      "verse": 5,
      "text": "Ya sunkuya ya duba ciki ya ga ƙyallayen lilin ne kwance a can amma bai shiga ba."
    },
    {
      "verse": 6,
      "text": "Sa’an nan Siman Bitrus, wanda yake bayansa, ya iso ya kuwa wuce cikin kabarin. Ya ga ƙyallayen lilin kwance a can,"
    },
    {
      "verse": 7,
      "text": "haka ma zanen binnewar da aka naɗe kan Yesu da shi. Zanen a naɗe yake shi kaɗai, a keɓe da lilin ɗin."
    },
    {
      "verse": 8,
      "text": "A ƙarshe sai almajirin nan, wanda ya kai kabarin da farko, shi ma ya shiga. Ya gani ya kuma gaskata."
    },
    {
      "verse": 9,
      "text": "(Har yanzu ba su fahimci Nassin nan da ya ce lalle ne Yesu yă tashi daga matattu ba.)"
    },
    {
      "verse": 10,
      "text": "Sai almajiran suka koma zuwa inda suke zama. Yesu ya bayyana ga Maryamu Magdalin (Mattiyu 28.1-10; Markus 16.1-8; Luka 24.1-12)"
    },
    {
      "verse": 11,
      "text": "Maryamu kuwa ta tsaya a bakin kabarin daga waje tana kuka. Da tana cikin kuka, sai ta sunkuya ta leƙa cikin kabarin,"
    },
    {
      "verse": 12,
      "text": "sai ta ga waɗansu mala’iku biyu saye da fararen tufafi, zaune a inda dā gawar Yesu take, ɗaya wajen kai ɗayan kuma wajen ƙafafu."
    },
    {
      "verse": 13,
      "text": "Suka tambaye ta cewa, “Mace, don me kike kuka?” Ta ce, “Sun ɗauke Ubangijina, ban kuma san inda suka ajiye shi ba.”"
    },
    {
      "verse": 14,
      "text": "Da ta faɗin haka, sai ta juya ta ga Yesu tsaye, sai dai ba tă gane cewa Yesu ne ba."
    },
    {
      "verse": 15,
      "text": "Sai ya ce, “Mace, don me kike kuka? Wa kike nema?” Ta yi tsammani shi ne mai aikin lambun, sai ta ce, “Ranka yă daɗe, in kai ne ka ɗauke shi, gaya mini inda ka ajiye shi, in je in ɗauke shi.”"
    },
    {
      "verse": 16,
      "text": "Yesu ya ce mata, “Maryamu.” Sai ta juya wajensa ta ɗaga murya ta ce da Arameyanci, “ Rabboni!” (Wanda yake nufin “Malam”)."
    },
    {
      "verse": 17,
      "text": "Yesu ya ce, “Kada ki riƙe ni, gama ban riga na koma wajen Uba tukuna ba. A maimako, ki tafi wajen ’yan’uwana ki gaya musu, ‘Ina komawa wajen Ubana da Ubanku, wajen Allahna da kuma Allahnku.’ ”"
    },
    {
      "verse": 18,
      "text": "Sai Maryamu Magdalin ta wajen almajiran da labari cewa, “Na ga Ubangiji!” Ta kuma gaya musu cewa ya faɗa mata waɗannan abubuwa. Yesu ya bayyana ga almajiransa (Mattiyu 28.16-20; Markus 16.14-18; Luka 24.36-49)"
    },
    {
      "verse": 19,
      "text": "Da Yamman ranar farko ta mako, sa’ad da almajiran suna tare, ƙofofi kuma suna a kulle saboda tsoron Yahudawa, sai ga Yesu ya zo ya tsaya a tsakiyarsu ya ce, “Salama tă kasance tare da ku!”"
    },
    {
      "verse": 20,
      "text": "Bayan ya faɗa haka, sai ya nuna musu hannuwansa da gefensa. Sai almajiran suka yi farin ciki ƙwarai da suka ga Ubangiji."
    },
    {
      "verse": 21,
      "text": "Sai Yesu ya sāke ce musu, “Salama tă kasance tare da ku! Kamar yadda Uba ya aiko ni, haka ni ma ina aikan ku.”"
    },
    {
      "verse": 22,
      "text": "Da wannan sai ya hura musu numfashinsa ya ce, “Ku karɓi Ruhu Mai Tsarki."
    },
    {
      "verse": 23,
      "text": "Duk wanda kuka gafarta wa zunubansa, an gafarta masa ke nan. Duk wanda ba ku gafarta wa ba kuwa, ba a gafarta masa ba ke nan.” Yesu ya bayyana ga Toma"
    },
    {
      "verse": 24,
      "text": "Toma kuwa (wanda ake kira Didaimus), ɗaya daga cikin Sha Biyun, ba ya tare da almajiran sa’ad da Yesu ya zo."
    },
    {
      "verse": 25,
      "text": "Saboda haka sauran almajiran suka ce masa, “Ai, mun ga Ubangiji!” Amma ya ce musu, “Ina, ai, sai na ga ramin ƙusa a hannuwansa na sa yatsata a inda ƙusoshi suka kasance, na kuma sa hannuna a gefensa, in ba haka ba, ba zan gaskata ba.”"
    },
    {
      "verse": 26,
      "text": "Bayan mako guda, har wa yau almajiransa suna cikin gidan, Toma kuwa yana tare da su. Ko da yake ƙofofi suna kulle, sai ga Yesu ya zo ya tsaya a tsakiyarsu ya ce, “Salama tă kasance tare da ku!”"
    },
    {
      "verse": 27,
      "text": "Sa’an nan ya ce wa Toma, “Sa yatsarka nan; dubi hannuwana. Miƙa hannunka ka sa a gefena. Ka daina shakka ka gaskata.”"
    },
    {
      "verse": 28,
      "text": "Toma ya ce masa, “Ya Ubangijina da Allahna!”"
    },
    {
      "verse": 29,
      "text": "Sai Yesu ya ce masa, “Wato ka gaskata saboda ka gan ni ne, masu albarka ne waɗanda ba su gan ni ba, amma suka gaskata.”"
    },
    {
      "verse": 30,
      "text": "Yesu ya yi waɗansu abubuwan banmamaki da yawa a gaban almajiransa da ba a rubuta a wannan littafi ba."
    },
    {
      "verse": 31,
      "text": "An dai rubuta waɗannan ne don ku gaskata Yesu ne Kiristi, Ɗan Allah kuma ta wurin gaskatawa ku sami rai a cikin sunansa."
    }
  ]
}