{
  "bookId": "psalms",
  "book": "Zabura",
  "chapter": 12,
  "verses": [
    {
      "verse": 1,
      "text": "Ka taimaka, Ubangiji, gama masu tsoron Allah ba sa nan kuma; masu aminci sun ɓace daga cikin mutane."
    },
    {
      "verse": 2,
      "text": "Kowa yana yi wa maƙwabcinsa ƙarya; zaƙin bakinsu maganar ƙarya ce suna cike da ruɗu a zukatansu."
    },
    {
      "verse": 3,
      "text": "Bari Ubangiji yă yanke dukan zaƙin bakinsu da kuma kowane harshe mai fariya,"
    },
    {
      "verse": 4,
      "text": "masu cewa, “Da harsunanmu za mu yi nasara; leɓunanmu za su kāre mu, wane ne maigidanmu?”"
    },
    {
      "verse": 5,
      "text": "“Saboda danniyar marasa ƙarfi da kuma nishin masu bukata, zan tashi yanzu,” in ji Ubangiji. “Zan kāre su daga masu yin musu sharri.”"
    },
    {
      "verse": 6,
      "text": "Kalmomin Ubangiji kuwa ba su da kuskure, kamar azurfan da aka tace cikin matoyan yumɓu, aka tsabtacce sau bakwai."
    },
    {
      "verse": 7,
      "text": "Ya Ubangiji, za ka kiyaye mu lafiya ka tsare mu daga irin mutanen nan har abada."
    },
    {
      "verse": 8,
      "text": "Mugaye suna yawo a sake sa’ad da ake girmama abin da ba shi da kyau a cikin mutane."
    }
  ]
}