{
  "bookId": "psalms",
  "book": "Zabura",
  "chapter": 92,
  "verses": [
    {
      "verse": 1,
      "text": "Yana da kyau a yabi Ubangiji a kuma yi kiɗi ga sunanka, ya Mafi Ɗaukaka,"
    },
    {
      "verse": 2,
      "text": "don a yi shelar ƙaunarka da safe amincinka kuma da dare,"
    },
    {
      "verse": 3,
      "text": "da kiɗin molo mai tsirkiya goma da kuma ƙarar garaya."
    },
    {
      "verse": 4,
      "text": "Gama ka sa na yi murna ta wurin ayyukanka, ya Ubangiji; na rera don farin ciki saboda ayyukan hannuwanka."
    },
    {
      "verse": 5,
      "text": "Ina misalin ayyukanka, ya Ubangiji, tunaninka da zurfi suke ƙwarai!"
    },
    {
      "verse": 6,
      "text": "Mutum marar azanci ba zai sani ba, wawa ba zai gane ba,"
    },
    {
      "verse": 7,
      "text": "cewa ko da yake mugaye suna girma kamar ciyawa kuma dukan masu aikata mugunta suna haɓaka, za a hallaka su har abada."
    },
    {
      "verse": 8,
      "text": "Amma kai, ya Ubangiji, za a ɗaukaka har abada."
    },
    {
      "verse": 9,
      "text": "Gama tabbatacce abokan gābanka, ya Ubangiji, tabbatacce abokan gābanka za su hallaka; za a watsar da dukan masu aikata mugunta."
    },
    {
      "verse": 10,
      "text": "Ka ɗaukaka ƙahona kamar na ɓauna; an zubo mai masu kyau a kaina."
    },
    {
      "verse": 11,
      "text": "Idanuna sun ga fāɗuwar maƙiyana; kunnuwana sun ji kukan mugayen maƙiyana."
    },
    {
      "verse": 12,
      "text": "Adalai za su haɓaka kamar itacen dabino, za su yi girma kama al’ul na Lebanon;"
    },
    {
      "verse": 13,
      "text": "da aka daddasa a gidan Ubangiji, za su haɓaka a filayen gidan Allahnmu."
    },
    {
      "verse": 14,
      "text": "Za su ci gaba da ba da ’ya’ya a tsufansu, za su kasance ɗanye kuma kore shar,"
    },
    {
      "verse": 15,
      "text": "suna shela cewa, “ Ubangiji adali ne; shi ne Dutsena, kuma babu mugunta a cikinsa.”"
    }
  ]
}