{
  "bookId": "psalms",
  "book": "Ìwé Saamu",
  "chapter": 102,
  "verses": [
    {
      "verse": 1,
      "text": "Gbọ́ àdúrà mi, Olúwa, jẹ́ kí igbe ẹ̀bẹ̀ mi kí ó wá sí ọ̀dọ̀ rẹ."
    },
    {
      "verse": 2,
      "text": "Má ṣe pa ojú rẹ mọ́ kúrò lọ́dọ̀ mi ní ọjọ́ tí èmi wà nínú ìpọ́njú. Dẹ etí rẹ sí mi; nígbà tí mo bá pè, dá mi lóhùn kíákíá."
    },
    {
      "verse": 3,
      "text": "Nítorí tí ọjọ́ mi run bí èéfín; egungun mi sì jóná bí ààrò."
    },
    {
      "verse": 4,
      "text": "Àyà mi lù, ó sì rọ bí i koríko; mo gbàgbé láti jẹ oúnjẹ mi."
    },
    {
      "verse": 5,
      "text": "Nítorí ohùn ìkérora mi, egungun mi lẹ̀ mọ́ ẹran-ara mi."
    },
    {
      "verse": 6,
      "text": "Èmi dàbí ẹyẹ igún ní ijù: èmi dàbí òwìwí ibi ahoro."
    },
    {
      "verse": 7,
      "text": "Èmi dìde; èmi dàbí ẹyẹ lórí ilé."
    },
    {
      "verse": 8,
      "text": "Ní ọjọ́ gbogbo, àwọn ọ̀tá ológoṣẹ́ mi ń gàn mí; àwọn tí ń ṣe ìkanra sí mi ń fi orúkọ mi bú."
    },
    {
      "verse": 9,
      "text": "Èmi jẹ eérú gẹ́gẹ́ bí oúnjẹ mi, èmi sì da ohun mímu mi pọ̀ pẹ̀lú omijé."
    },
    {
      "verse": 10,
      "text": "Nítorí ìbínú ríru rẹ, nítorí ìwọ ti gbé mi sókè, ìwọ sì gbé mi ṣánlẹ̀."
    },
    {
      "verse": 11,
      "text": "Ọjọ́ mi dàbí òjìji àṣálẹ́ èmi sì rọ bí koríko."
    },
    {
      "verse": 12,
      "text": "Ṣùgbọ́n ìwọ, Olúwa, ni yóò dúró láéláé; ìrántí rẹ láti ìran dé ìran."
    },
    {
      "verse": 13,
      "text": "Ìwọ ó dìde ìwọ ó sì ṣàánú fún Sioni, nítorí ìgbà àti ṣe ojúrere sí i; àkókò náà ti dé."
    },
    {
      "verse": 14,
      "text": "Nítorí tí àwọn òkúta jẹ́ inú dídùn sí àwọn ìránṣẹ́ rẹ; wọ́n sì káàánú erùpẹ̀ rẹ."
    },
    {
      "verse": 15,
      "text": "Àwọn kèfèrí yóò bẹ̀rù orúkọ Olúwa, gbogbo ọba ayé yóò máa bẹ̀rù ògo rẹ."
    },
    {
      "verse": 16,
      "text": "Torí tí Olúwa yóò gbé Sioni ró, yóò farahàn nínú ògo rẹ̀."
    },
    {
      "verse": 17,
      "text": "Yóò dáhùn àdúrà àwọn aláìní; kì yóò sì gan ẹ̀bẹ̀ wọn."
    },
    {
      "verse": 18,
      "text": "Jẹ́ kí a kọ èyí fún ìran tí ń bọ̀, àwọn ènìyàn tí a kò tí ì dá yóò yin Olúwa:"
    },
    {
      "verse": 19,
      "text": "“ Olúwa wo ilẹ̀ láti òkè mímọ́ rẹ̀ wá láti ọ̀run wá ni ó bojú wo ayé,"
    },
    {
      "verse": 20,
      "text": "láti gbọ́ ìrora ará túbú, láti tú àwọn tí a yàn sí ikú sílẹ̀.”"
    },
    {
      "verse": 21,
      "text": "Kí a lè sọ orúkọ Olúwa ní Sioni àti ìyìn rẹ̀ ní Jerusalẹmu."
    },
    {
      "verse": 22,
      "text": "Ní ìgbà tí a kó àwọn ènìyàn àti ìjọba pọ̀ láti máa sìn Olúwa."
    },
    {
      "verse": 23,
      "text": "Ní ipa ọ̀nà mi, ó rẹ agbára mi sílẹ̀, ó gé ọjọ́ mi kúrú."
    },
    {
      "verse": 24,
      "text": "Èmi sì wí pé: “Ọlọ́run mi, má ṣe mú mi kúrò ní agbede-méjì ọjọ́ mi; ọdún rẹ̀ ń lọ láti ìran dé ìran."
    },
    {
      "verse": 25,
      "text": "Ní ìbẹ̀rẹ̀ ní ìwọ fi ìpìlẹ̀ ayé sọlẹ̀, ọ̀run sì jẹ́ iṣẹ́ ọwọ́ rẹ."
    },
    {
      "verse": 26,
      "text": "Wọn yóò ṣègbé, wọn yóò parun, ṣùgbọ́n ìwọ yóò wà; gbogbo wọn ni yóò gbó bí aṣọ. Bí ẹ̀wù ni ìwọ yóò pààrọ̀ wọn wọn yóò sì di àpatì."
    },
    {
      "verse": 27,
      "text": "Ṣùgbọ́n ìwọ wà digbí síbẹ̀, ọdún rẹ kò sì ní òpin."
    },
    {
      "verse": 28,
      "text": "Àwọn ọmọ ìránṣẹ́ rẹ̀ yóò dúró ní iwájú rẹ pẹ́; a ó sì fi ẹsẹ̀ irú-ọmọ wọn sọlẹ̀ ní iwájú rẹ.”"
    }
  ]
}