{
  "bookId": "psalms",
  "book": "Ìwé Saamu",
  "chapter": 131,
  "verses": [
    {
      "verse": 1,
      "text": "Olúwa àyà mi kò gbéga, bẹ́ẹ̀ ni ojú mi kò gbé sókè: bẹ́ẹ̀ ni èmi kò fi ọwọ́ mi lé ọ̀ràn ńlá, tàbí lé ohun tí ó ga jù mí lọ."
    },
    {
      "verse": 2,
      "text": "Nítòótọ́ èmi mú ọkàn mi sinmi, mo sì mú un dákẹ́ jẹ́ẹ́, bí ọmọ tí a ti ọwọ́ ìyá rẹ̀ gbà ní ẹnu ọmú: ọkàn mi rí gẹ́gẹ́ bí ọmọ tí a já ní ẹnu ọmú."
    },
    {
      "verse": 3,
      "text": "Israẹli, ìwọ ní ìrètí ní ti Olúwa láti ìsinsin yìí lọ àti láéláé."
    }
  ]
}