{
  "bookId": "genesis",
  "book": "Jenesis",
  "chapter": 16,
  "verses": [
    {
      "verse": 1,
      "text": "Ma Serai nwunye Ebram, amụtaghị nwa. Serai nwere odibo nwanyị onye Ijipt, aha ya bụ Hega."
    },
    {
      "verse": 2,
      "text": "Ya mere ọ gwara Ebram sị, “Lee, ugbu a, Onyenwe anyị egbochiela m ịmụta ụmụ. Ugbu a, bakwuru nwanyị na-ejere m ozi. Ma eleghị anya, aga m esi na ya wulite ezinaụlọ m.” Ebram kweere ihe Serai kwuru."
    },
    {
      "verse": 3,
      "text": "Ya mere Serai nwunye Ebram, duuru Hega, odibo nwanyị ya, onye Ijipt, dunye Ebram ka ọ bụrụ nwunye ya. Ihe a mere na ngwụcha afọ iri site na mgbe Ebram bịara biri nʼala Kenan."
    },
    {
      "verse": 4,
      "text": "Ebram na Hega dinara. Hega tụụrụ ime. Ma mgbe Hega matara na ọ dịrịla ime, ọ malitere ileda nne ya ukwu bụ Serai anya."
    },
    {
      "verse": 5,
      "text": "Mgbe ahụ, Serai gwara Ebram sị, “Ọ bụ gị butere ahụhụ a m nọ nʼime ya. Ọ bụ m were nwaodibo nwanyị m kunye gị nʼaka, ma ugbu a ọ hụrụ na ọ dị ime, abụrụla m onye ọ na-eleda anya. Ka Onyenwe anyị kpee ikpe a nʼetiti mụ na gị.”"
    },
    {
      "verse": 6,
      "text": "Ebram zara Serai sị, “Lee, ohu gị nwanyị dị gị nʼaka. Jiri ya mee ihe ọbụla dị gị mma nʼanya.” Nʼihi nke a, Serai mesiri ya ihe ike, nke mere ka o si nʼebe Serai nọ gbapụ."
    },
    {
      "verse": 7,
      "text": "Ma mmụọ ozi Onyenwe anyị hụrụ ya nʼakụkụ isi iyi mmiri dị nʼọzara, nʼakụkụ ụzọ Shua,"
    },
    {
      "verse": 8,
      "text": "jụọ ya sị, “Hega, ohu nwanyị Serai, olee ebe i si bịa, olee ebe ka ị na-ejekwa?” Hega zara sị, “Ọ bụ site nʼihu nne m ukwu Serai ka m na-agba ọsọ.”"
    },
    {
      "verse": 9,
      "text": "Mmụọ ozi Onyenwe anyị gwara ya sị, “Laghachikwuru nne gị ukwu. Doo onwe gị nʼokpuru ya.”"
    },
    {
      "verse": 10,
      "text": "Mmụọ ozi Onyenwe anyị sịkwa ya, “Aga m amụba ụmụ gị, ka a hapụ inwe ike ịgụta ole ha dị.”"
    },
    {
      "verse": 11,
      "text": "Mmụọ ozi Onyenwe anyị gwakwara ya sị, “Ị dị ime ugbu a, ị ga-amụ nwa nwoke. Aha ị ga-agụ ya bụ Ishmel nʼihi na Onyenwe anyị anụla maka nhụju anya gị."
    },
    {
      "verse": 12,
      "text": "Nwoke dịka ịnyịnya ibu a na-azụghị azụ ka ọ ga-abụ. Ọ ga-emegide onye ọbụla, onye ọbụla ga-emegidekwa ya. Ọ ga-ebi nʼime ibu iro, megide ụmụnna ya niile.”"
    },
    {
      "verse": 13,
      "text": "Hega kpọkuru aha Onyenwe anyị, onye gwara ya okwu sị, “Ị bụ Chineke m na-ahụ m.” Nʼihi na Hega kwuru sị, “Ahụla m, ugbu a, onye ahụ na-ahụ m.”"
    },
    {
      "verse": 14,
      "text": "Ọ bụ ya mere e ji na-akpọ olulu mmiri ahụ, Bịa-Lahai-Rọị. Ọ ka dị ebe ahụ, nʼetiti Kadesh na Bered."
    },
    {
      "verse": 15,
      "text": "Emesịa, Hega mụtaara Ebram nwa nwoke. Ebram kpọrọ nwa nwoke ahụ Hega mụtaara ya Ishmel."
    },
    {
      "verse": 16,
      "text": "Ebram gbara iri afọ asatọ na isii mgbe Hega mụtaara ya Ishmel."
    }
  ]
}